check_print/__init__.py
check_print/main.py
tests/__init__.py
tests/test.py
check_print-0.1.5.dist-info/METADATA
check_print-0.1.5.dist-info/WHEEL
check_print-0.1.5.dist-info/entry_points.txt
check_print-0.1.5.dist-info/top_level.txt
check_print-0.1.5.dist-info/RECORD
